
[
    {"mode":"timer","m":10,"func":"exec/ts1"},
    {"mode":"explicit","y":2024,"M":1,"d":28,"H":23,"m":49,"s":0,"func":"halcmd","params":"write/uint/fan/255"},
    {"mode":"daily","H":23,"m":49,"s":0,"func":"halcmd","params":"write/uint/fan/255"},
    {"mode":"weekly","D":"sat","H":23,"m":49,"s":0,"func":"halcmd","params":"write/uint/fan/255"},
    {"mode":"weekly","D":"sat","H":23,"m":49,"s":0,"func":{"type":"halcmd","params":"write/uint/fan/255"}},

    {"mode":"daily","H":12,"func":"halcmd","params":"write/uint/tx433:D0/1"},

    {"mode":"explicit","y":2024,"M":1,"d":28,"H":23,"m":49,"s":0,"func":"halcmd","params":"write/uint/fan/255"},
    {"mode":"explicit","y":2024,"M":1,"d":28,"H":23,"m":49,"s":0,"func":"halcmd","params":"write/uint/fan/255"},
    {"mode":"explicit","y":2024,"M":1,"d":28,"H":23,"m":49,"s":0,"func":"halcmd","params":"write/uint/fan/255"},
    {"mode":"explicit","y":2024,"M":1,"d":28,"H":23,"m":49,"s":0,"func":"halcmd","params":"write/uint/fan/255"},
    {"mode":"explicit","y":2024,"M":1,"d":28,"H":23,"m":49,"s":0,"func":"halcmd","params":"write/uint/fan/255"},
    {"mode":"explicit","y":2024,"M":1,"d":28,"H":23,"m":49,"s":0,"func":"halcmd","params":"write/uint/fan/255"},
    {"mode":"explicit","y":2024,"M":1,"d":28,"H":23,"m":49,"s":0,"func":"halcmd","params":"write/uint/fan/255"},
    {"mode":"explicit","y":2024,"M":1,"d":28,"H":23,"m":49,"s":0,"func":"halcmd","params":"write/uint/fan/255"},
    {"mode":"explicit","y":2024,"M":1,"d":28,"H":23,"m":49,"s":0,"func":"halcmd","params":"write/uint/fan/255"},
    {"mode":"explicit","y":2024,"M":1,"d":28,"H":23,"m":49,"s":0,"func":"halcmd","params":"write/uint/fan/255"},
    {"mode":"explicit","y":2024,"M":1,"d":28,"H":23,"m":49,"s":0,"func":"halcmd","params":"write/uint/fan/255"},
    {"mode":"explicit","y":2024,"M":1,"d":28,"H":23,"m":49,"s":0,"func":"halcmd","params":"write/uint/fan/255"},
    {"mode":"explicit","y":2024,"M":1,"d":28,"H":23,"m":49,"s":0,"func":"halcmd","params":"write/uint/fan/255"},
    {"mode":"explicit","y":2024,"M":1,"d":28,"H":23,"m":49,"s":0,"func":"halcmd","params":"write/uint/fan/255"},
    {"mode":"explicit","y":2024,"M":1,"d":28,"H":23,"m":49,"s":0,"func":"halcmd","params":"write/uint/fan/255"},
    {"mode":"explicit","y":2024,"M":1,"d":28,"H":23,"m":49,"s":0,"func":"halcmd","params":"write/uint/fan/255"},
    {"mode":"explicit","y":2024,"M":1,"d":28,"H":23,"m":49,"s":0,"func":"halcmd","params":"write/uint/fan/255"},
    {"mode":"explicit","y":2024,"M":1,"d":28,"H":23,"m":49,"s":0,"func":"halcmd","params":"write/uint/fan/255"},
    {"mode":"explicit","y":2024,"M":1,"d":28,"H":23,"m":49,"s":0,"func":"halcmd","params":"write/uint/fan/255"},
    {"mode":"explicit","y":2024,"M":1,"d":28,"H":23,"m":49,"s":0,"func":"halcmd","params":"write/uint/fan/255"}
]
